data_lab/__init__.py
data_lab/hello_world.py
doyoung_ops-0.0.0.4.dist-info/METADATA
doyoung_ops-0.0.0.4.dist-info/WHEEL
doyoung_ops-0.0.0.4.dist-info/top_level.txt
doyoung_ops-0.0.0.4.dist-info/RECORD
