Metadata-Version: 2.1
Name: doyoung-ops
Version: 0.0.0.4
Summary: hello world package.
Home-page: UNKNOWN
Author: 
Author-email: 
License: Uram
Platform: UNKNOWN
Requires-Python: >=3.8
Requires-Dist: boto3
Requires-Dist: pymongo
